unification/__init__.py
unification/_version.py
unification/core.py
unification/dispatch.py
unification/match.py
unification/more.py
unification/utils.py
unification/variable.py
logical_unification-0.4.3.dist-info/LICENSE.txt
logical_unification-0.4.3.dist-info/METADATA
logical_unification-0.4.3.dist-info/WHEEL
logical_unification-0.4.3.dist-info/top_level.txt
logical_unification-0.4.3.dist-info/RECORD
