Metadata-Version: 2.1
Name: logical-unification
Version: 0.4.3
Summary: Logical unification in Python
Home-page: http://github.com/pythological/unification/
Maintainer: Brandon T. Willard
Maintainer-email: brandonwillard+unification@gmail.com
License: BSD
Keywords: unification logic-programming dispatch
Platform: UNKNOWN
Classifier: Development Status :: 5 - Production/Stable
Classifier: Intended Audience :: Science/Research
Classifier: Intended Audience :: Developers
Classifier: License :: OSI Approved :: BSD License
Classifier: Operating System :: OS Independent
Classifier: Programming Language :: Python
Classifier: Programming Language :: Python :: 3
Classifier: Programming Language :: Python :: 3.6
Classifier: Programming Language :: Python :: 3.7
Classifier: Programming Language :: Python :: 3.8
Classifier: Programming Language :: Python :: Implementation :: CPython
Classifier: Programming Language :: Python :: Implementation :: PyPy
Classifier: Topic :: Software Development :: Libraries
Requires-Python: >=3.6
